locawise/__init__.py
locawise/__main__.py
locawise/androidutils.py
locawise/dictutils.py
locawise/diffutils.py
locawise/envutils.py
locawise/errors.py
locawise/fileutils.py
locawise/langutils.py
locawise/llm.py
locawise/localization/__init__.py
locawise/localization/config.py
locawise/localization/format.py
locawise/localization/localize.py
locawise/localization/prompts.py
locawise/lockfile.py
locawise/parsing.py
locawise/processor.py
locawise/regexutils.py
locawise/serialization.py
locawise-1.3.1.dist-info/LICENSE.md
locawise-1.3.1.dist-info/METADATA
locawise-1.3.1.dist-info/WHEEL
locawise-1.3.1.dist-info/RECORD
