Metadata-Version: 2.3
Name: locawise
Version: 1.3.1
Summary: 
Author: Emre Safak
Author-email: aemresafak@gmail.com
Requires-Python: >=3.13
Classifier: Programming Language :: Python :: 3
Classifier: Programming Language :: Python :: 3.13
Requires-Dist: aiofiles (>=24.1.0,<25.0.0)
Requires-Dist: google-genai (>=1.10.0,<2.0.0)
Requires-Dist: jproperties (>=2.1.2,<3.0.0)
Requires-Dist: lxml (>=5.4.0,<6.0.0)
Requires-Dist: openai (>=1.76.0,<2.0.0)
Requires-Dist: pycountry (>=24.6.1,<25.0.0)
Requires-Dist: pydantic (>=2.11.3,<3.0.0)
Requires-Dist: pytest (>=8.3.5,<9.0.0)
Requires-Dist: pytest-asyncio (>=0.26.0,<0.27.0)
Requires-Dist: pytest-mock (>=3.14.0,<4.0.0)
Requires-Dist: pyyaml (>=6.0.2,<7.0.0)
Requires-Dist: tenacity (>=9.1.2,<10.0.0)
Requires-Dist: xxhash (>=3.5.0,<4.0.0)
